dssatsim/__init__.py
dssatsim/envs.py
dssatsim/explain_dssat_outputs.py
dssatsim/iopairs/readme.txt
dssatsim/references/MCSE2002.SQX
dssatsim/references/MSKB0001.WTH
dssatsim/run_dssat_exp_cli.py
dssatsim/serverlessdb/agxdbv1/KALAMAZOO_3KFARMS_WEATHER_DATA_TABLE_1km.parquet
dssatsim/serverlessdb/agxdbv1/KALAMAZOO_COUNTY_WEATHER_DATA_TABLE_1km.parquet
dssatsim/serverlessdb/agxdbv1/US_SOIL_DATA_TABLE_10km.parquet
dssatsim/static/ALL_DSSAT_CDE_FILES.csv
dssatsim/static/CUL_SPE_ECO_COEFFS_DEFINITIONS.csv
dssatsim/static/OFFICIAL_DSSAT_CROP_CODES.csv
dssatsim/utils.py
dssatsim-0.1.3.dist-info/METADATA
dssatsim-0.1.3.dist-info/WHEEL
dssatsim-0.1.3.dist-info/RECORD
