Metadata-Version: 2.1
Name: dssatsim
Version: 0.1.3
Summary: Simple saptiotemporal DSSAT simulator
Author: JK
Author-email: kpodojos@msu.edu
Requires-Python: >=3.10,<4.0
Classifier: Programming Language :: Python :: 3
Classifier: Programming Language :: Python :: 3.10
Classifier: Programming Language :: Python :: 3.11
Classifier: Programming Language :: Python :: 3.12
Classifier: Programming Language :: Python :: 3.13
Requires-Dist: dssattools (==2.1.4)
Requires-Dist: fastparquet (==2024.5.0)
Requires-Dist: geopandas (==0.14.4)
Requires-Dist: pandas (==2.2.2)
Requires-Dist: pygeohash (==1.2.0)
Requires-Dist: pyproj (==3.6.1)
Requires-Dist: python-dotenv (==1.0.1)
Requires-Dist: shapely (==2.0.5)
